typing_exe/__init__.py
typing_exe/annotations.py
typing_exe/decorators.py
typing_exe/early_return.py
typing_exe/parameter_data.py
typing_exe/util.py
typing_exe-1.0.0.dist-info/LICENSE
typing_exe-1.0.0.dist-info/METADATA
typing_exe-1.0.0.dist-info/WHEEL
typing_exe-1.0.0.dist-info/top_level.txt
typing_exe-1.0.0.dist-info/RECORD
