Metadata-Version: 2.1
Name: typing-exe
Version: 1.0.0
Summary: Executable typehints for Python: make assertions about and/or modify parameters & return values
Author: Sebastian Müller
Author-email: sebastian.nicolas.mueller@gmail.com
Project-URL: repository, https://github.com/snimu/typing-exe
Keywords: parameters,return-value,typing,assert,modify,decorator,typehint
Classifier: Programming Language :: Python
Classifier: Programming Language :: Python :: 3
Classifier: Programming Language :: Python :: 3.8
Classifier: Programming Language :: Python :: 3.9
Classifier: Programming Language :: Python :: 3.10
Classifier: Programming Language :: Python :: 3.11
Classifier: License :: OSI Approved :: MIT License
Classifier: Operating System :: OS Independent
Requires-Python: >=3.8
License-File: LICENSE
